odoo9_addon_account_move_base_import-9.0.1.0.0.99.dev112-py3.8-nspkg.pth
odoo_addons/account_move_base_import/README.rst
odoo_addons/account_move_base_import/__init__.py
odoo_addons/account_move_base_import/__openerp__.py
odoo_addons/account_move_base_import/data/completion_rule_data.xml
odoo_addons/account_move_base_import/data/statement.csv
odoo_addons/account_move_base_import/data/statement.xls
odoo_addons/account_move_base_import/i18n/account_move_base_import.pot
odoo_addons/account_move_base_import/i18n/am.po
odoo_addons/account_move_base_import/i18n/ar.po
odoo_addons/account_move_base_import/i18n/bg.po
odoo_addons/account_move_base_import/i18n/bs.po
odoo_addons/account_move_base_import/i18n/ca.po
odoo_addons/account_move_base_import/i18n/ca_ES.po
odoo_addons/account_move_base_import/i18n/cs.po
odoo_addons/account_move_base_import/i18n/da.po
odoo_addons/account_move_base_import/i18n/da_DK.po
odoo_addons/account_move_base_import/i18n/de.po
odoo_addons/account_move_base_import/i18n/el_GR.po
odoo_addons/account_move_base_import/i18n/en_AU.po
odoo_addons/account_move_base_import/i18n/en_GB.po
odoo_addons/account_move_base_import/i18n/es.po
odoo_addons/account_move_base_import/i18n/es_AR.po
odoo_addons/account_move_base_import/i18n/es_CL.po
odoo_addons/account_move_base_import/i18n/es_CO.po
odoo_addons/account_move_base_import/i18n/es_CR.po
odoo_addons/account_move_base_import/i18n/es_DO.po
odoo_addons/account_move_base_import/i18n/es_EC.po
odoo_addons/account_move_base_import/i18n/es_ES.po
odoo_addons/account_move_base_import/i18n/es_MX.po
odoo_addons/account_move_base_import/i18n/es_PE.po
odoo_addons/account_move_base_import/i18n/es_PY.po
odoo_addons/account_move_base_import/i18n/es_VE.po
odoo_addons/account_move_base_import/i18n/et.po
odoo_addons/account_move_base_import/i18n/eu.po
odoo_addons/account_move_base_import/i18n/fa.po
odoo_addons/account_move_base_import/i18n/fi.po
odoo_addons/account_move_base_import/i18n/fr.po
odoo9_addon_account_move_base_import-9.0.1.0.0.99.dev112.dist-info/METADATA
odoo9_addon_account_move_base_import-9.0.1.0.0.99.dev112.dist-info/WHEEL
odoo9_addon_account_move_base_import-9.0.1.0.0.99.dev112.dist-info/namespace_packages.txt
odoo9_addon_account_move_base_import-9.0.1.0.0.99.dev112.dist-info/top_level.txt
odoo9_addon_account_move_base_import-9.0.1.0.0.99.dev112.dist-info/RECORD
